gmcache/__init__.py
gmcache/utils.py
gmcache-1.0.4.dist-info/LICENSE
gmcache-1.0.4.dist-info/METADATA
gmcache-1.0.4.dist-info/WHEEL
gmcache-1.0.4.dist-info/top_level.txt
gmcache-1.0.4.dist-info/RECORD
